slink/__init__.py
slink/seed_functions.py
slink/examples/__init__.py
slink-0.0.2.dist-info/LICENSE
slink-0.0.2.dist-info/METADATA
slink-0.0.2.dist-info/WHEEL
slink-0.0.2.dist-info/top_level.txt
slink-0.0.2.dist-info/RECORD
