Metadata-Version: 2.1
Name: slink
Version: 0.0.2
Summary: Generate sequences
Home-page: https://github.com/otosense/slink
Author: OtoSense
License: apache-2.0
Platform: any
